buoy/__init__.py
buoy/cli.py
buoy/main.py
buoy/models/__init__.py
buoy/models/aframe.py
buoy/models/amplfi.py
buoy/utils/__init__.py
buoy/utils/data.py
buoy/utils/html.py
buoy/utils/pe.py
buoy/utils/plotting.py
buoy/utils/preprocessing.py
ml4gw_buoy-0.4.1.dist-info/licenses/LICENSE
ml4gw_buoy-0.4.1.dist-info/METADATA
ml4gw_buoy-0.4.1.dist-info/WHEEL
ml4gw_buoy-0.4.1.dist-info/entry_points.txt
ml4gw_buoy-0.4.1.dist-info/top_level.txt
ml4gw_buoy-0.4.1.dist-info/RECORD
