Metadata-Version: 2.4
Name: ml4gw-buoy
Version: 0.4.1
Summary: Deploy Aframe and AMPLFI models over open data
Author-email: Will Benoit <benoi090@umn.edu>
Classifier: License :: OSI Approved :: GNU General Public License v3 (GPLv3)
Classifier: Programming Language :: Python :: 3.10
Classifier: Programming Language :: Python :: 3.11
Classifier: Programming Language :: Python :: 3.12
Requires-Python: <3.13,>=3.10
License-File: LICENSE
Requires-Dist: amplfi>=0.5.5
Requires-Dist: ml4gw>=0.7.4
Requires-Dist: jsonargparse~=4.40
Requires-Dist: h5py~=3.12
Requires-Dist: numpy<2.0.0
Requires-Dist: matplotlib==3.9.4
Requires-Dist: gwpy==3.0.12
Requires-Dist: ligo-skymap<3,>=2.2.2
Requires-Dist: huggingface_hub~=0.30
Dynamic: license-file
